cdk_lambda_powertools_python_layer/__init__.py
cdk_lambda_powertools_python_layer/py.typed
cdk_lambda_powertools_python_layer/_jsii/__init__.py
cdk_lambda_powertools_python_layer/_jsii/cdk-lambda-powertools-python-layer@2.1.0.jsii.tgz
cdk_lambda_powertools_python_layer-2.1.0.dist-info/LICENSE
cdk_lambda_powertools_python_layer-2.1.0.dist-info/METADATA
cdk_lambda_powertools_python_layer-2.1.0.dist-info/WHEEL
cdk_lambda_powertools_python_layer-2.1.0.dist-info/top_level.txt
cdk_lambda_powertools_python_layer-2.1.0.dist-info/RECORD
