Metadata-Version: 2.1
Name: cdk-lambda-powertools-python-layer
Version: 2.1.0
Summary: A lambda layer for AWS Powertools for python
Home-page: https://github.com/aws-samples/cdk-lambda-powertools-python-layer.git
Author: Amazon Web Services
License: MIT-0
Project-URL: Source, https://github.com/aws-samples/cdk-lambda-powertools-python-layer.git
Classifier: Intended Audience :: Developers
Classifier: Operating System :: OS Independent
Classifier: Programming Language :: JavaScript
Classifier: Programming Language :: Python :: 3 :: Only
Classifier: Programming Language :: Python :: 3.7
Classifier: Programming Language :: Python :: 3.8
Classifier: Programming Language :: Python :: 3.9
Classifier: Programming Language :: Python :: 3.10
Classifier: Typing :: Typed
Classifier: Development Status :: 5 - Production/Stable
Classifier: License :: OSI Approved
Requires-Python: ~=3.7
License-File: LICENSE
Requires-Dist: aws-cdk-lib (<3.0.0,>=2.24.1)
Requires-Dist: constructs (<11.0.0,>=10.0.5)
Requires-Dist: jsii (<2.0.0,>=1.65.0)
Requires-Dist: publication (>=0.0.3)
Requires-Dist: typeguard (~=2.13.3)
